PyInterrail/__init__.py
PyInterrail/client.py
PyInterrail/config.py
PyInterrail/service.py
PyInterrail/stop_location.py
PyInterrail/trip.py
PyInterrail-1.2.dist-info/LICENSE
PyInterrail-1.2.dist-info/METADATA
PyInterrail-1.2.dist-info/WHEEL
PyInterrail-1.2.dist-info/top_level.txt
PyInterrail-1.2.dist-info/RECORD
